skarf/__init__.py
skarf/_version.py
skarf/covariance/__init__.py
skarf/covariance/_pyspi.py
skarf/var/__init__.py
skarf/var/_base.py
skarf/var/_covariance.py
skarf/var/_linear.py
skarf/var/_multi.py
skarf/var/_utils.py
skarf-0.1.0.dist-info/licenses/LICENSE
skarf-0.1.0.dist-info/METADATA
skarf-0.1.0.dist-info/WHEEL
skarf-0.1.0.dist-info/top_level.txt
skarf-0.1.0.dist-info/RECORD
