Metadata-Version: 2.4
Name: skarf
Version: 0.1.0
Summary: scikit autoregressive models for functional connectivity
Author-email: Connor Lane <connor.lane858@gmail.com>
License: MIT License
Project-URL: Homepage, https://github.com/childmindresearch/skarf
Project-URL: Issues, https://github.com/childmindresearch/skarf/issues
Classifier: Development Status :: 3 - Alpha
Classifier: Intended Audience :: Developers
Classifier: Topic :: Scientific/Engineering
Classifier: Programming Language :: Python :: 3
Classifier: Programming Language :: Python :: 3.11
Classifier: Programming Language :: Python :: 3.12
Classifier: Programming Language :: Python :: 3.13
Classifier: Programming Language :: Python :: 3.14
Classifier: License :: OSI Approved :: MIT License
Classifier: Operating System :: POSIX
Classifier: Operating System :: Unix
Classifier: Operating System :: MacOS
Classifier: Operating System :: Microsoft :: Windows
Requires-Python: >=3.11
License-File: LICENSE
Requires-Dist: numpy<2
Requires-Dist: pandas
Requires-Dist: scikit-learn>=1.6.0
Requires-Dist: scipy
Provides-Extra: pyspi
Requires-Dist: pyspi; extra == "pyspi"
Requires-Dist: ipython<9; extra == "pyspi"
Requires-Dist: setuptools; extra == "pyspi"
Dynamic: license-file
